{
    "morning": [
        ["****-**-** 06:00:00", "****-**-** 09:59:59" ]
    ]
    , "midnight": [
          ["****-**-** 20:00:00", "****-**-** 23:59:59" ]
        , ["****-**-** 00:00:00", "****-**-** 04:59:59" ]
    ]
    , "summer": [
          ["****-07-01 00:00:00", "****-09-30 23:59:59"]
    ]
    , "winter": [
          ["****-11-01 00:00:00", "****-12-31 23:59:59"]
        , ["****-01-01 00:00:00", "****-02-29 23:59:59"]
    ]
    , "wrong_winter": [
          ["****-11-01 00:00:00", "****-02-29 23:59:59"]
    ]
    , "christmas": [
          ["****-12-25 00:00:00", "****-12-25 23:59:59"]
    ]
}
